MANIFEST.in
requirements.txt
setup.py
test_requirements.txt
version.txt
cloudshell/__init__.py
cloudshell/traffic/__init__.py
cloudshell/traffic/teravm/__init__.py
cloudshell/traffic/teravm/vblade/__init__.py
cloudshell/traffic/teravm/vblade/configuration_attributes_structure.py
cloudshell/traffic/teravm/vblade/autoload/__init__.py
cloudshell/traffic/teravm/vblade/autoload/models.py
cloudshell_tg_teravm_vblade.egg-info/PKG-INFO
cloudshell_tg_teravm_vblade.egg-info/SOURCES.txt
cloudshell_tg_teravm_vblade.egg-info/dependency_links.txt
cloudshell_tg_teravm_vblade.egg-info/requires.txt
cloudshell_tg_teravm_vblade.egg-info/top_level.txt