Metadata-Version: 1.0
Name: cloudshell-tg-teravm-vblade
Version: 1.0.1
Summary: QualiSystems Python package
Home-page: https://github.com/QualiSystems/cloudshell-tg-teravm-vblade
Author: QualiSystems
Author-email: info@qualisystems.com
License: UNKNOWN
Platform: UNKNOWN
